tvault/__init__.py
tvault/model_diff.py
tvault/model_log.py
tvault/parse_utils.py
tvault/torchvault.py
tvault-0.3.16.dist-info/LICENSE
tvault-0.3.16.dist-info/METADATA
tvault-0.3.16.dist-info/WHEEL
tvault-0.3.16.dist-info/entry_points.txt
tvault-0.3.16.dist-info/top_level.txt
tvault-0.3.16.dist-info/RECORD
