Metadata-Version: 2.1
Name: tvault
Version: 0.3.16
Summary: Log and find diffs between pytorch models
Home-page: https://github.com/vessl-ai/tvault.git
Author: Saeyoon Oh
Author-email: david@vessl.ai
License: MIT
Platform: UNKNOWN
Requires-Python: >=3
License-File: LICENSE
Requires-Dist: GitPython
Requires-Dist: astunparse
Requires-Dist: openai
Requires-Dist: prettytable
